jira_creator/__init__.py
jira_creator/rh_jira.py
jira_creator/core/env_fetcher.py
jira_creator/core/view_helpers.py
jira_creator/exceptions/__init__.py
jira_creator/exceptions/exceptions.py
jira_creator/plugins/__init__.py
jira_creator/plugins/add_comment_plugin.py
jira_creator/plugins/add_flag_plugin.py
jira_creator/plugins/add_to_sprint_plugin.py
jira_creator/plugins/assign_plugin.py
jira_creator/plugins/base.py
jira_creator/plugins/block_plugin.py
jira_creator/plugins/blocked_plugin.py
jira_creator/plugins/change_plugin.py
jira_creator/plugins/change_type_plugin.py
jira_creator/plugins/clone_issue_plugin.py
jira_creator/plugins/create_issue_plugin.py
jira_creator/plugins/edit_issue_plugin.py
jira_creator/plugins/get_sprint_plugin.py
jira_creator/plugins/list_issues_plugin.py
jira_creator/plugins/list_sprints_plugin.py
jira_creator/plugins/migrate_plugin.py
jira_creator/plugins/open_issue_plugin.py
jira_creator/plugins/quarterly_connection_plugin.py
jira_creator/plugins/registry.py
jira_creator/plugins/remove_flag_plugin.py
jira_creator/plugins/remove_sprint_plugin.py
jira_creator/plugins/search_plugin.py
jira_creator/plugins/search_users_plugin.py
jira_creator/plugins/set_acceptance_criteria_plugin.py
jira_creator/plugins/set_component_plugin.py
jira_creator/plugins/set_priority_plugin.py
jira_creator/plugins/set_project_plugin.py
jira_creator/plugins/set_status_plugin.py
jira_creator/plugins/set_story_epic_plugin.py
jira_creator/plugins/set_story_points_plugin.py
jira_creator/plugins/set_summary_plugin.py
jira_creator/plugins/set_workstream_plugin.py
jira_creator/plugins/setter_base.py
jira_creator/plugins/unassign_plugin.py
jira_creator/plugins/unblock_plugin.py
jira_creator/plugins/validate_issue_plugin.py
jira_creator/plugins/view_issue_plugin.py
jira_creator/plugins/view_user_plugin.py
jira_creator/plugins/vote_story_points_plugin.py
jira_creator/providers/__init__.py
jira_creator/providers/ai_provider.py
jira_creator/providers/bart_provider.py
jira_creator-1.0.11.dist-info/licenses/LICENSE
jira_creator-1.0.11.dist-info/METADATA
jira_creator-1.0.11.dist-info/WHEEL
jira_creator-1.0.11.dist-info/entry_points.txt
jira_creator-1.0.11.dist-info/top_level.txt
jira_creator-1.0.11.dist-info/RECORD
