Metadata-Version: 2.4
Name: jira-creator
Version: 1.0.11
Summary: CLI and tools to automate JIRA issue creation
Author-email: David O Neill <dmz.oneill@gmail.com>
License-Expression: Apache-2.0
Requires-Python: >=3.11
License-File: LICENSE
Dynamic: license-file
